{
  "generatedAt": "2026-03-27T18:04:58.068Z",
  "totalRows": 123663,
  "sports": [
    {
      "sport": "Baseball",
      "earliestLoadedDate": "2026-03-20",
      "latestLoadedDate": "2026-03-27",
      "rowCount": 15612
    },
    {
      "sport": "Basketball",
      "earliestLoadedDate": "2026-03-20",
      "latestLoadedDate": "2026-03-27",
      "rowCount": 20898
    },
    {
      "sport": "Football",
      "earliestLoadedDate": "2025-12-13",
      "latestLoadedDate": "2026-02-08",
      "rowCount": 74454
    },
    {
      "sport": "Hockey",
      "earliestLoadedDate": "2026-03-20",
      "latestLoadedDate": "2026-03-27",
      "rowCount": 12699
    }
  ],
  "byMarket": [
    {
      "market": "spread",
      "rowCount": 41221,
      "gradedPercent": 0.9559933043836879,
      "closingLinePercent": 0.9924310424298295
    },
    {
      "market": "moneyline",
      "rowCount": 41221,
      "gradedPercent": 0.9771475704131389,
      "closingLinePercent": 0.9924310424298295
    },
    {
      "market": "total",
      "rowCount": 41221,
      "gradedPercent": 0.9560660828218627,
      "closingLinePercent": 0.9924310424298295
    }
  ]
}