{
  "generatedAt": "2026-03-20T06:36:17.094Z",
  "totalRows": 17571,
  "sports": [
    {
      "sport": "Baseball",
      "earliestLoadedDate": "2025-03-20",
      "latestLoadedDate": "2026-03-20",
      "rowCount": 8298
    },
    {
      "sport": "Basketball",
      "earliestLoadedDate": "2025-03-15",
      "latestLoadedDate": "2026-03-20",
      "rowCount": 6363
    },
    {
      "sport": "Football",
      "earliestLoadedDate": "2025-12-13",
      "latestLoadedDate": "2026-02-08",
      "rowCount": 1413
    },
    {
      "sport": "Hockey",
      "earliestLoadedDate": "2025-03-20",
      "latestLoadedDate": "2026-03-20",
      "rowCount": 1497
    }
  ],
  "byMarket": [
    {
      "market": "spread",
      "rowCount": 5857,
      "gradedPercent": 0.8823629844630357,
      "closingLinePercent": 0.9298275567696773
    },
    {
      "market": "moneyline",
      "rowCount": 5857,
      "gradedPercent": 0.9458767287007,
      "closingLinePercent": 0.9392180297080417
    },
    {
      "market": "total",
      "rowCount": 5857,
      "gradedPercent": 0.8825337203346423,
      "closingLinePercent": 0.929998292641284
    }
  ]
}