{
  "generatedAt": "2026-03-22T12:58:46.275Z",
  "totalRows": 22671,
  "sports": [
    {
      "sport": "Baseball",
      "earliestLoadedDate": "2025-03-20",
      "latestLoadedDate": "2026-03-22",
      "rowCount": 9330
    },
    {
      "sport": "Basketball",
      "earliestLoadedDate": "2025-03-15",
      "latestLoadedDate": "2026-03-22",
      "rowCount": 7824
    },
    {
      "sport": "Football",
      "earliestLoadedDate": "2025-12-13",
      "latestLoadedDate": "2026-02-08",
      "rowCount": 3528
    },
    {
      "sport": "Hockey",
      "earliestLoadedDate": "2025-03-20",
      "latestLoadedDate": "2026-03-22",
      "rowCount": 1989
    }
  ],
  "byMarket": [
    {
      "market": "spread",
      "rowCount": 7557,
      "gradedPercent": 0.8903003837501654,
      "closingLinePercent": 0.9348947995236205
    },
    {
      "market": "moneyline",
      "rowCount": 7557,
      "gradedPercent": 0.9806801640862777,
      "closingLinePercent": 0.9367473865290459
    },
    {
      "market": "total",
      "rowCount": 7557,
      "gradedPercent": 0.8908296943231441,
      "closingLinePercent": 0.9350271271668652
    }
  ]
}